genice_cif/__init__.py
genice_cif/lattices/__init__.py
genice_cif/lattices/cif.py
genice_cif/lattices/zeolite.py
genice_cif-0.2.1.dist-info/METADATA
genice_cif-0.2.1.dist-info/WHEEL
genice_cif-0.2.1.dist-info/entry_points.txt
genice_cif-0.2.1.dist-info/top_level.txt
genice_cif-0.2.1.dist-info/RECORD
