Metadata-Version: 2.1
Name: genice-cif
Version: 0.2.1
Summary: CIF reader plugin for GenIce.
Home-page: https://github.com/vitroid/genice-cif/
Author: Masakazu Matsumoto
Author-email: vitroid@gmail.com
License: MIT
Keywords: genice,CIF
Platform: UNKNOWN
Classifier: Development Status :: 4 - Beta
Classifier: Intended Audience :: Developers
Classifier: Programming Language :: Python
Classifier: Programming Language :: Python :: 3.5
Requires-Dist: cif2ice (>=0.2.2)
Requires-Dist: GenIce (>=0.25)
